<?xml version="1.0" encoding="UTF-8"?>
<beans xmlns="http://www.springframework.org/schema/beans"
	xmlns:xsi="http://www.w3.org/2001/XMLSchema-instance" xmlns:context="http://www.springframework.org/schema/context"
	xmlns:mvc="http://www.springframework.org/schema/mvc"
	xsi:schemaLocation="http://www.springframework.org/schema/beans http://www.springframework.org/schema/beans/spring-beans-4.0.xsd
		http://www.springframework.org/schema/context http://www.springframework.org/schema/context/spring-context-4.0.xsd
		http://www.springframework.org/schema/mvc http://www.springframework.org/schema/mvc/spring-mvc-4.0.xsd">




	<bean id="dateFormat" class="java.text.SimpleDateFormat">
		<constructor-arg value="yyyy-MM-dd" />
	</bean>


	<bean id="accountManager"
		class="es.unileon.InteresesOrdinarios.service.SimpleAccountManager">
		<property name="account">

			<ref bean="account1" />
		</property>
	</bean>

	<bean id="account1" class="es.unileon.InteresesOrdinarios.domain.Account">
		<property name="accountDescription" value="1234-2096-33-9517408632 Titular: Paula" />
		<property name="movementBalance1" value="15200.80" />
		<property name="dateMov1">
			<bean factory-bean="dateFormat" factory-method="parse">
				<constructor-arg value="2014-04-24" />
			</bean>
		</property>
		<property name="movementBalance2" value="15000.80" />
		<property name="dateMov2">
			<bean factory-bean="dateFormat" factory-method="parse">
				<constructor-arg value="2014-04-30" />
			</bean>
		</property>
		<property name="movementBalance3" value="16536.65" />
		<property name="dateMov3">
			<bean factory-bean="dateFormat" factory-method="parse">
				<constructor-arg value="2014-05-5" />
			</bean>
		</property>
		<property name="movementBalance4" value="16412.78" />
		<property name="dateMov4">
			<bean factory-bean="dateFormat" factory-method="parse">
				<constructor-arg value="2014-05-12" />
			</bean>
		</property>
		<property name="movementBalance5" value="36412.78" />
		<property name="dateMov5">
			<bean factory-bean="dateFormat" factory-method="parse">
				<constructor-arg value="2014-05-16" />
			</bean>
		</property>

	</bean>



	<bean id="messageSource"
		class="org.springframework.context.support.ResourceBundleMessageSource">
		<property name="basename" value="messages" />
	</bean>



	<!-- Scans the classpath of this application for @Components to deploy as 
		beans -->
	<context:component-scan base-package="es.unileon.InteresesOrdinarios.web" />

	<!-- Configures the @Controller programming model -->
	<mvc:annotation-driven />


	<bean id="viewResolver"
		class="org.springframework.web.servlet.view.InternalResourceViewResolver">
		<property name="viewClass"
			value="org.springframework.web.servlet.view.JstlView"></property>
		<property name="prefix" value="/WEB-INF/views/"></property>
		<property name="suffix" value=".jsp"></property>
	</bean>


</beans>

